amortization/__init__.py
amortization/amortize.py
amortization/amount.py
amortization/enums.py
amortization/period.py
amortization/schedule.py
amortization-2.5.0.dist-info/LICENSE
amortization-2.5.0.dist-info/METADATA
amortization-2.5.0.dist-info/WHEEL
amortization-2.5.0.dist-info/entry_points.txt
amortization-2.5.0.dist-info/RECORD
