Metadata-Version: 2.3
Name: amortization
Version: 2.5.0
Summary: Python library for calculating amortizations and generating amortization schedules
License: MIT
Keywords: amortization
Author: Ronie Martinez
Author-email: ronmarti18@gmail.com
Requires-Python: >=3.9
Classifier: Development Status :: 5 - Production/Stable
Classifier: License :: OSI Approved :: MIT License
Classifier: Topic :: Office/Business :: Financial :: Accounting
Classifier: Topic :: Scientific/Engineering :: Mathematics
Classifier: Topic :: Software Development :: Libraries :: Python Modules
Classifier: Programming Language :: Python :: 3
Classifier: Programming Language :: Python :: 3.9
Classifier: Programming Language :: Python :: 3.10
Classifier: Programming Language :: Python :: 3.11
Classifier: Programming Language :: Python :: 3.12
Classifier: Programming Language :: Python :: 3.13
Classifier: Programming Language :: Python :: Implementation :: CPython
Requires-Dist: tabulate (>=0.9.0,<0.10.0)
Project-URL: Donate, https://www.buymeacoffee.com/roniemartinez
